{"stat.useItem.divinerpg.everbright":2,"stat.flyOneCm":5035,"stat.walkOneCm":11724,"stat.useItem.divinerpg.ender_watcher_pumpkin":1,"stat.pickup.divinerpg.crab_claw":1,"stat.jump":11,"stat.swimOneCm":95,"stat.playOneMinute":4450,"stat.sneakTime":9,"stat.useItem.divinerpg.arksiane_wrathsword":7,"stat.damageDealt":1900,"stat.useItem.divinerpg.aqua_torch":5,"stat.crouchOneCm":1,"stat.timeSinceDeath":4450,"stat.killEntity.Squid":1,"stat.mobKills":5,"stat.sprintOneCm":70,"stat.useItem.minecraft.stone_slab2":3,"stat.diveOneCm":1404,"stat.killEntity.divinerpg.crab":4,"stat.pickup.divinerpg.aqua_torch":1}